Metadata-Version: 1.1
Name: CSpipe
Version: 0.052
Summary: ChIP-Seq pipe
Home-page: https://pypi.python.org/pypi/CSpipe
Author: Yingxiang Li
Author-email: xlccalyx@gmail.com
License: GPLv3
Download-URL: https://pypi.python.org/pypi/CSpipe
Keywords: ChIP-Seq pipe
Platform: UNKNOWN
Classifier: Development Status :: 3 - Alpha
Classifier: Intended Audience :: Developers
Classifier: Topic :: Software Development :: Build Tools
Classifier: License :: OSI Approved :: GNU General Public License v3 (GPLv3)
Classifier: Programming Language :: Python :: 2.7
